{
    "data": [
        {
            "id": 1,
            "name": "Altenjo",
            "country": "Portugal",
            "rating": 4.2,
            "reviews": 123,
            "tags": [
                "Sights & Landmarks",
                "Food & Drink",
                "Activities"
            ],
            "tripTypes": [
                "Business",
                "Couples"
            ],
            "webUrl": "https://www.tripadvisor.com/Tourism-g189101-Alentejo-Vacations.html?m=66827",
            "related": {
                "wines": [
                    {
                        "id": 1,
                        "name": "Pêra-Manca Tinto 1990",
                        "country": "Portugal",
                        "region": "Altenjo",
                        "winery": "Cartuxa",
                        "rating": 4.7,
                        "reviews": 79,
                        "type": "Red",
                        "image": "https://images.vivino.com/thumbs/L33jsYUuTMWTMy3KoqQyXg_pb_x300.png"
                    }
                ],
                "vineyards": [
                    {
                        "id": 23,
                        "name": "Chafariz do vinho",
                        "country": "Portugal",
                        "price": 2,
                        "rating": 4.5,
                        "reviews": 8,
                        "image": "https://s3-media0.fl.yelpcdn.com/bphoto/8qkn16tQEEAdaE8dy_qbhw/o.jpg"
                    }
                ]
            }
        },
        {
            "id": 2,
            "name": "Napa Valley",
            "country": "United States",
            "rating": 4.9,
            "reviews": 693,
            "tags": [
                "Food & Drink"
            ],
            "tripTypes": [
                "Friends",
                "Solo",
                "Couples"
            ],
            "webUrl": "https://www.tripadvisor.com/Tourism-g580460-Napa_Valley_California-Vacations.html",
            "related": {
                "wines": [
                    {
                        "id": 3,
                        "name": "Wraith Cabernet Sauvignon 2013",
                        "country": "United States",
                        "region": "Napa Valley",
                        "winery": "Hundred Acre",
                        "rating": 4.9,
                        "reviews": 68,
                        "type": "Red",
                        "image": "https://images.vivino.com/thumbs/PBhGMcRNQ7aVnVNr7VgnWA_pb_x300.png"
                    }
                ],
                "vineyards": [
                    {
                        "id": 1,
                        "name": "The Austin Winery",
                        "country": "United States",
                        "price": 2,
                        "rating": 4.0,
                        "reviews": 127,
                        "image": "https://s3-media1.fl.yelpcdn.com/bphoto/DIwTmoCWHMG_gSe4TzPSEA/o.jpg"
                    },
                    {
                        "id": 6,
                        "name": "Agua Dulce Winery",
                        "country": "United States",
                        "price": 3,
                        "rating": 4.5,
                        "reviews": 359,
                        "image": "https://s3-media0.fl.yelpcdn.com/bphoto/CBJMN8WKe9_GUKhgYBG8Mw/o.jpg"
                    }
                ]
            }
        },
        {
            "id": 3,
            "name": "Reims",
            "country": "France",
            "rating": 4.9,
            "reviews": 693,
            "tags": [
                "Sights & Landmarks",
                "Food & Drink"
            ],
            "tripTypes": [
                "Family",
                "Couples"
            ],
            "webUrl": "https://www.tripadvisor.com/Tourism-g187137-Reims_Marne_Grand_Est-Vacations.html",
            "related": {
                "wines": [
                    {
                        "id": 10,
                        "name": "Bâtard-Montrachet Grand Cru 2012",
                        "country": "France",
                        "region": "Bâtard-Montrachet Grand Cru",
                        "winery": "Olivier Leflaive",
                        "rating": 4.8,
                        "reviews": 55,
                        "type": "White",
                        "image": "https://images.vivino.com/thumbs/pWOdFPoyQ427uoHW_l941g_pb_x300.png"
                    }
                ],
                "vineyards": [
                    {
                        "id": 56,
                        "name": "Bessich",
                        "country": "France",
                        "price": 2,
                        "rating": 4.9,
                        "reviews": 3,
                        "image": "https://s3-media0.fl.yelpcdn.com/bphoto/O141yrwXhR9TYy8ZRG81_w/o.jpg"
                    },
                    {
                        "id": 634,
                        "name": "Les Caves du Louvre",
                        "country": "France",
                        "price": 1,
                        "rating": 4.3,
                        "reviews": 41,
                        "image": "https://s3-media0.fl.yelpcdn.com/bphoto/yNdcNPZ0q08RkAugL-iGCQ/o.jpg"
                    }
                ]
            }
        },
        {
            "id": 4,
            "name": "Bourgogne-Franche-Comté",
            "country": "France",
            "rating": 4.5,
            "reviews": 203,
            "tags": [
                "Sights & Landmarks",
                "Food & Drink",
                "Activities"
            ],
            "tripTypes": [
                "Business",
                "Couples",
                "Solo"
            ],
            "webUrl": "https://www.tripadvisor.com/Tourism-g11038854-Bourgogne_Franche_Comte-Vacations.html",
            "related": {
                "wines": [
                    {
                        "id": 143,
                        "name": "Cristal Rosé Brut Champagne (Millésimé) 2004",
                        "country": "France",
                        "region": "Champagne",
                        "winery": "Louis Roederer",
                        "rating": 4.7,
                        "reviews": 229,
                        "type": "Sparkling",
                        "image": "https://images.vivino.com/thumbs/QcdE7SdeR3G1nzcAS4Scgg_pb_x300.png"
                    },
                    {
                        "id": 202,
                        "name": "Château Romassan Rosé (Coeur de Grain) 2018",
                        "country": "France",
                        "region": "Champagne",
                        "winery": "Bandol",
                        "rating": 4.3,
                        "reviews": 155,
                        "type": "Dessert",
                        "image": "https://images.vivino.com/thumbs/tE2hMYcUTnuNw1l0_BFZlA_pb_x300.png"
                    }
                ],
                "vineyards": [
                    {
                        "id": 634,
                        "name": "Les Caves du Louvre",
                        "country": "France",
                        "price": 1,
                        "rating": 4.3,
                        "reviews": 41,
                        "image": "https://s3-media0.fl.yelpcdn.com/bphoto/yNdcNPZ0q08RkAugL-iGCQ/o.jpg"
                    }
                ]
            }
        },
        {
            "id": 5,
            "name": "Central Portugal",
            "country": "Portugal",
            "rating": 4.6,
            "reviews": 323,
            "tags": [
                "Food & Drink",
                "Activities"
            ],
            "tripTypes": [
                "Business",
                "Solo",
                "Friends"
            ],
            "webUrl": "https://www.tripadvisor.com/Tourism-g3932272-Central_Portugal-Vacations.html",
            "related": {
                "wines": [
                    {
                        "id": 1,
                        "name": "Pêra-Manca Tinto 1990",
                        "country": "Portugal",
                        "region": "Altenjo",
                        "winery": "Cartuxa",
                        "rating": 4.7,
                        "reviews": 79,
                        "type": "Red",
                        "image": "https://images.vivino.com/thumbs/L33jsYUuTMWTMy3KoqQyXg_pb_x300.png"
                    }
                ],
                "vineyards": [
                    {
                        "id": 23,
                        "name": "Chafariz do vinho",
                        "country": "Portugal",
                        "price": 2,
                        "rating": 4.5,
                        "reviews": 8,
                        "image": "https://s3-media0.fl.yelpcdn.com/bphoto/8qkn16tQEEAdaE8dy_qbhw/o.jpg"
                    }
                ]
            }
        }
    ]
}